yata/__init__.py
yata/fields.py
yata/loaders.py
yata/util.py
yata-0.0.1.dist-info/METADATA
yata-0.0.1.dist-info/RECORD
yata-0.0.1.dist-info/WHEEL
yata-0.0.1.dist-info/top_level.txt
